grafana_backup/__init__.py
grafana_backup/api_checks.py
grafana_backup/archive.py
grafana_backup/azure_storage_download.py
grafana_backup/azure_storage_upload.py
grafana_backup/cli.py
grafana_backup/commons.py
grafana_backup/constants.py
grafana_backup/create_alert_channel.py
grafana_backup/create_alert_rule.py
grafana_backup/create_annotation.py
grafana_backup/create_contact_point.py
grafana_backup/create_dashboard.py
grafana_backup/create_datasource.py
grafana_backup/create_folder.py
grafana_backup/create_library_element.py
grafana_backup/create_org.py
grafana_backup/create_snapshot.py
grafana_backup/create_team.py
grafana_backup/create_team_member.py
grafana_backup/create_user.py
grafana_backup/dashboardApi.py
grafana_backup/delete.py
grafana_backup/delete_alert_channels.py
grafana_backup/delete_annotations.py
grafana_backup/delete_dashboards.py
grafana_backup/delete_datasources.py
grafana_backup/delete_folders.py
grafana_backup/delete_library_elements.py
grafana_backup/delete_snapshots.py
grafana_backup/delete_team_members.py
grafana_backup/delete_teams.py
grafana_backup/gcs_download.py
grafana_backup/gcs_upload.py
grafana_backup/grafanaSettings.py
grafana_backup/influx.py
grafana_backup/make_users_viewers.py
grafana_backup/pause_alerts.py
grafana_backup/restore.py
grafana_backup/restore_user_permissions.py
grafana_backup/s3_common.py
grafana_backup/s3_download.py
grafana_backup/s3_upload.py
grafana_backup/save.py
grafana_backup/save_alert_channels.py
grafana_backup/save_alert_rules.py
grafana_backup/save_annotations.py
grafana_backup/save_contact_points.py
grafana_backup/save_dashboard_versions.py
grafana_backup/save_dashboards.py
grafana_backup/save_datasources.py
grafana_backup/save_folders.py
grafana_backup/save_library_elements.py
grafana_backup/save_notification_policies.py
grafana_backup/save_orgs.py
grafana_backup/save_snapshots.py
grafana_backup/save_team_members.py
grafana_backup/save_teams.py
grafana_backup/save_users.py
grafana_backup/tools.py
grafana_backup_mood-1.4.4.dist-info/LICENSE
grafana_backup_mood-1.4.4.dist-info/METADATA
grafana_backup_mood-1.4.4.dist-info/WHEEL
grafana_backup_mood-1.4.4.dist-info/entry_points.txt
grafana_backup_mood-1.4.4.dist-info/top_level.txt
grafana_backup_mood-1.4.4.dist-info/RECORD
