Metadata-Version: 2.1
Name: grafana-backup-mood
Version: 1.4.4
Summary: A Python-based application to backup Grafana settings using the Grafana API
Home-page: https://github.com/ysde/grafana-backup-tool
Author: author
Author-email: ysde108@gmail.com
License-File: LICENSE
Requires-Dist: requests
Requires-Dist: docopt
Requires-Dist: boto3 (==1.35.99)
Requires-Dist: azure-storage-blob
Requires-Dist: google-cloud-storage
Requires-Dist: influxdb
Requires-Dist: packaging
